metovlogs/__init__.py
metovlogs/lib.py
metovlogs-0.1.7.dist-info/licenses/LICENSE
metovlogs-0.1.7.dist-info/METADATA
metovlogs-0.1.7.dist-info/WHEEL
metovlogs-0.1.7.dist-info/top_level.txt
metovlogs-0.1.7.dist-info/RECORD
