Metadata-Version: 2.4
Name: metovlogs
Version: 0.1.7
Summary: Dead simple Python logging.
Home-page: https://github.com/metov/metovlogs
Author: Azat Akhmetov
Author-email: azatinfo@yandex.com
Classifier: Programming Language :: Python :: 3
Classifier: Development Status :: 3 - Alpha
Classifier: License :: OSI Approved :: MIT License
License-File: LICENSE
Requires-Dist: coloredlogs
Dynamic: author
Dynamic: author-email
Dynamic: classifier
Dynamic: description
Dynamic: description-content-type
Dynamic: home-page
Dynamic: license-file
Dynamic: requires-dist
Dynamic: summary
